fw_file/__init__.py
fw_file/base.py
fw_file/bruker.py
fw_file/eeg.py
fw_file/exif.py
fw_file/ge.py
fw_file/jpg.py
fw_file/json.py
fw_file/nifti.py
fw_file/philips.py
fw_file/png.py
fw_file/py.typed
fw_file/siemens.py
fw_file/utils.py
fw_file/dicom/__init__.py
fw_file/dicom/config.py
fw_file/dicom/dcmdict.py
fw_file/dicom/dicom.py
fw_file/dicom/fixers.py
fw_file/dicom/reader.py
fw_file/dicom/series.py
fw_file/dicom/testing.py
fw_file/dicom/utils.py
fw_file/dicom/validation.py
fw_file/dicom/standard/editions.json
fw_file/dicom/standard/2023c/json/dict_info.json
fw_file/dicom/standard/2023c/json/iod_info.json
fw_file/dicom/standard/2023c/json/module_info.json
fw_file/dicom/standard/2023c/json/uid_info.json
fw_file/dicom/standard/2023c/json/version
fw_file/dicom/standard/2024e/json/dict_info.json
fw_file/dicom/standard/2024e/json/iod_info.json
fw_file/dicom/standard/2024e/json/module_info.json
fw_file/dicom/standard/2024e/json/uid_info.json
fw_file/dicom/standard/2024e/json/version
fw_file-4.1.3.dist-info/METADATA
fw_file-4.1.3.dist-info/WHEEL
fw_file-4.1.3.dist-info/licenses/LICENSE
fw_file-4.1.3.dist-info/RECORD
