Metadata-Version: 2.4
Name: fw-file
Version: 4.1.3
Summary: Unified data-file interface
Project-URL: Repository, https://gitlab.com/flywheel-io/tools/lib/fw-file
Project-URL: Documentation, https://gitlab.com/flywheel-io/tools/lib/fw-file
Author-email: Flywheel <support@flywheel.io>
License-Expression: MIT
License-File: LICENSE
Keywords: Bruker,CT,DICOM,EEG,Flywheel,GE,JPEG,JPG,MR,NIfTI,PARREC,PET,PFile,PNG,PTD,ParaVision,Philips,RAW,Siemens,extract,file,medical,metadata,parse
Classifier: Topic :: Scientific/Engineering :: Medical Science Apps.
Classifier: Topic :: Software Development :: Libraries :: Python Modules
Requires-Python: ~=3.10
Requires-Dist: dicom-validator>=0.4.1
Requires-Dist: faker>=30.6.0
Requires-Dist: fw-meta>=4.0.0
Requires-Dist: fw-utils>=4.3.4
Requires-Dist: natsort<9,>=8.0.0
Requires-Dist: pydantic-settings<3,>=2.0.3
Requires-Dist: pydantic<3,>=2.4.2
Requires-Dist: pydicom<4,>=3.0.1
Requires-Dist: python-dateutil<3,>=2.8.1
Requires-Dist: pyyaml>=5.4.1
Provides-Extra: all
Requires-Dist: dotty-dict<2,>=1.3.1; extra == 'all'
Requires-Dist: edfio<1,>=0; extra == 'all'
Requires-Dist: edflib-python<2,>=1.0.8; extra == 'all'
Requires-Dist: eeglabio<1,>=0; extra == 'all'
Requires-Dist: mne[hdf5]<2,>=1.8.0; extra == 'all'
Requires-Dist: nibabel>=4.0.2; extra == 'all'
Requires-Dist: piexif<2,>=1.1.3; extra == 'all'
Requires-Dist: pillow>=9; extra == 'all'
Requires-Dist: pybv<1,>=0; extra == 'all'
Requires-Dist: pypng<1,>=0; extra == 'all'
Provides-Extra: eeg
Requires-Dist: edfio<1,>=0; extra == 'eeg'
Requires-Dist: edflib-python<2,>=1.0.8; extra == 'eeg'
Requires-Dist: eeglabio<1,>=0; extra == 'eeg'
Requires-Dist: mne[hdf5]<2,>=1.8.0; extra == 'eeg'
Requires-Dist: pybv<1,>=0; extra == 'eeg'
Provides-Extra: jpg
Requires-Dist: piexif<2,>=1.1.3; extra == 'jpg'
Requires-Dist: pillow>=9; extra == 'jpg'
Provides-Extra: json
Requires-Dist: dotty-dict<2,>=1.3.1; extra == 'json'
Provides-Extra: nifti
Requires-Dist: nibabel>=4.0.2; extra == 'nifti'
Provides-Extra: png
Requires-Dist: piexif<2,>=1.1.3; extra == 'png'
Requires-Dist: pillow>=9; extra == 'png'
Requires-Dist: pypng<1,>=0; extra == 'png'
